{
  "id": "cloud_report_1772287663169_36d554d9",
  "type": "cloud_report",
  "data": {
    "file_path": "C:\\Users\\DELL\\Downloads\\dfg\\merge\\reports\\ECG_Report_12_1_20260228_182450.pdf",
    "metadata": {
      "filename": "ECG_Report_12_1_20260228_182450.pdf",
      "uploaded_at": "2026-02-28T19:37:43.169087",
      "file_size": 406940,
      "file_type": ".pdf"
    },
    "cloud_service": "s3"
  },
  "priority": 2,
  "queued_at": "2026-02-28T14:07:43.169087Z",
  "retry_count": 4,
  "status": "pending"
}