{
  "21121": {
    "phone": "21121",
    "contact": "21121",
    "signup_date": "2026-01-12"
  },
  "312": {
    "phone": "312",
    "contact": "312",
    "signup_date": "2026-01-12"
  },
  "tyty": {
    "phone": "tyty",
    "contact": "tyty",
    "signup_date": "2026-01-17"
  },
  "sfgh": {
    "phone": "sfgh",
    "contact": "sfgh",
    "signup_date": "2026-01-21"
  },
  "11": {
    "phone": "11",
    "contact": "11",
    "signup_date": "2026-02-09"
  },
  "343": {
    "phone": "343",
    "contact": "343",
    "signup_date": "2026-02-16"
  },
  "55": {
    "phone": "55",
    "contact": "55",
    "signup_date": "2026-02-21"
  },
  "44": {
    "phone": "44",
    "contact": "44",
    "signup_date": "2026-02-28"
  }
}